{
  "objectsData": [
    {
      "name": "PLAYERBULLET",
      "count": 100,
      "path": "Bullets/Player_Normal"
    },
    {
      "name": "PLAYERSHOTGUNBULLET",
      "count": 20,
      "path": "Bullets/Player_Shotgun"
    },
    {
      "name": "PLAYERROCKETBULLET",
      "count": 3,
      "path": "Bullets/Player_Rocket"
    },
    {
      "name": "PLAYERDIVEEXPLOSION",
      "count": 3,
      "path": "Bullets/Explosion_Dive_Attack"
    },
    {
      "name": "ENEMYBULLET",
      "count": 50,
      "path": "Bullets/Enemy_Normal"
    },
    {
      "name": "BREAKOBJECT",
      "count": 100,
      "path": "Objects/Break_Object"
    },
    {
      "name": "METALOBJECT",
      "count": 100,
      "path": "Objects/Metal"
    },
    {
      "name": "ITEM_GUN",
      "count": 10,
      "path": "Objects/Item_Gun"
    }
  ]
}
